gci/__init__.py
gci/component-descriptor.json-schema.yaml
gci/componentmodel.py
gci/oci.py
gardener_component_model-0.0.98.dist-info/METADATA
gardener_component_model-0.0.98.dist-info/WHEEL
gardener_component_model-0.0.98.dist-info/top_level.txt
gardener_component_model-0.0.98.dist-info/RECORD
