Metadata-Version: 2.1
Name: gardener-component-model
Version: 0.0.98
Summary: Gardener Component Model
Requires-Python: >=3.9
Requires-Dist: dacite
Requires-Dist: jsonschema
Requires-Dist: python-dateutil
Requires-Dist: PyYaml
